{"assets":{"447D3461C58C508D2CD0D2E68FF39170":{"url":{"web":"assets/1CB2B260-F03A-415B-B9FF-BD3FD473CA1B.svgmap"},"height":1080,"movie":"scanning-saccade.mp4-0.0000-4.1050","width":1920,"type":"texture","assetRequest":{"byGlyphStyle":0,"deliveryStyle":0,"chunkIndex":1,"type":"chunk","chunkCount":1,"stageIndex":0,"stageCount":1},"index":4},"1A8579A2224D6E44976C40D1C8926D33":{"type":"texture","index":2,"assetRequest":{"type":"slide","state":"contents","slide":"1CB2B260-F03A-415B-B9FF-BD3FD473CA1B"},"url":{"web":"assets/1CB2B260-F03A-415B-B9FF-BD3FD473CA1B.svgmap"},"width":732,"height":34},"7ECCBBADA95A810EA2401298EFB05CC2":{"type":"texture","index":1,"assetRequest":{"type":"slide","state":"contents","slide":"1CB2B260-F03A-415B-B9FF-BD3FD473CA1B"},"url":{"web":"assets/1CB2B260-F03A-415B-B9FF-BD3FD473CA1B.svgmap"},"width":1923,"height":1082},"844C2FF7E8E8A2713DCDCAE67EAAF34C":{"type":"texture","index":5,"assetRequest":{"type":"slide","state":"outgoing","slide":"1CB2B260-F03A-415B-B9FF-BD3FD473CA1B"},"url":{"web":"assets/1CB2B260-F03A-415B-B9FF-BD3FD473CA1B.svgmap"},"width":1920,"height":1080},"5BA6DF7ACEF516F7DAB78587CF30CE20":{"type":"texture","index":0,"assetRequest":{"type":"slide","state":"contents","slide":"1CB2B260-F03A-415B-B9FF-BD3FD473CA1B"},"url":{"web":"assets/1CB2B260-F03A-415B-B9FF-BD3FD473CA1B.svgmap"},"width":1920,"height":1080},"BA892B329981A31005A36E8FA9C1120D":{"type":"texture","index":3,"assetRequest":{"type":"slide","state":"contents","slide":"1CB2B260-F03A-415B-B9FF-BD3FD473CA1B"},"url":{"web":"assets/1CB2B260-F03A-415B-B9FF-BD3FD473CA1B.svgmap"},"width":383,"height":34},"scanning-saccade.mp4-0.0000-4.1050":{"type":"video","index":0,"assetRequest":{},"url":{"web":"assets/scanning-saccade.mp4-0.0000-4.1050.m4v","native":"assets/scanning-saccade.mp4-0.0000-4.1050.m4v"},"width":1280,"height":720},"31875A1B00F89E47B08D92D0E8479265":{"type":"texture","index":6,"assetRequest":{"type":"slide","state":"incoming","slide":"4668512C-6780-472E-B6C2-27EC6919681F"},"url":{"web":"assets/1CB2B260-F03A-415B-B9FF-BD3FD473CA1B.svgmap"},"width":1920,"height":1080}},"events":[{"effects":[{"beginTime":0,"baseLayer":{"animations":[],"initialState":{"affineTransform":[1,0,0,1,0,0],"masksToBounds":false,"rotation":0,"scale":1,"position":{"pointX":960.0000001373422,"pointY":540},"width":1920,"sublayerTransform":[1,0,0,0,0,1,0,0,0,0,1,0,0,0,0,1],"contentsRect":{"y":0,"x":0,"width":1,"height":1},"opacity":1,"edgeAntialiasingMask":251658240,"height":1080,"hidden":false,"anchorPoint":{"pointX":0.5,"pointY":0.5}},"objectID":"B0C3572B-4AB1-4B8C-BDD2-B1EFA918CDC2","layers":[{"animations":[],"initialState":{"affineTransform":[1,0,0,1,0,0],"masksToBounds":false,"rotation":0,"scale":1,"position":{"pointX":959.9999998626578,"pointY":540},"width":1920,"sublayerTransform":[1,0,0,0,0,1,0,0,0,0,1,-0.0003500791246677598,0,0,0,1],"contentsRect":{"y":0,"x":0,"width":1,"height":1},"opacity":1,"edgeAntialiasingMask":251658240,"height":1080,"hidden":false,"anchorPoint":{"pointX":0.4999999999284676,"pointY":0.5}},"layers":[{"animations":[{"timeOffset":0,"beginTime":1e-100,"repeatCount":0,"animations":[{"timeOffset":0,"from":{"scalar":true},"beginTime":0,"repeatCount":0,"fillMode":"removed","property":"isPlaying","autoreverses":false,"duration":0.01,"to":{"scalar":true}},{"timeOffset":0,"from":{"scalar":false},"beginTime":0,"repeatCount":0,"fillMode":"removed","property":"hidden","autoreverses":false,"duration":0.01,"to":{"scalar":false}}],"fillMode":"both","autoreverses":false,"duration":0.01}],"layers":[],"texturedRectangle":{"isBackgroundTexture":true,"singleTextureOpacity":1,"textureType":5,"textBaseline":0,"textXHeight":0,"isVerticalText":false},"initialState":{"affineTransform":[1,0,0,1,0,0],"masksToBounds":false,"rotation":0,"scale":1,"position":{"pointX":960.4999998626578,"pointY":540},"width":1923,"sublayerTransform":[1,0,0,0,0,1,0,0,0,0,1,0,0,0,0,1],"contentsRect":{"y":0,"x":0,"width":1,"height":1},"opacity":1,"edgeAntialiasingMask":0,"height":1082,"hidden":false,"anchorPoint":{"pointX":0.5,"pointY":0.5}},"texture":"7ECCBBADA95A810EA2401298EFB05CC2"}]}]},"effects":[{"beginTime":0,"baseLayer":{"animations":[],"initialState":{"affineTransform":[1,0,0,1,0,0],"masksToBounds":false,"rotation":0,"scale":1,"position":{"pointX":960.0000001373422,"pointY":540},"width":1920,"sublayerTransform":[1,0,0,0,0,1,0,0,0,0,1,0,0,0,0,1],"contentsRect":{"y":0,"x":0,"width":1,"height":1},"opacity":1,"edgeAntialiasingMask":251658240,"height":1080,"hidden":false,"anchorPoint":{"pointX":0.5,"pointY":0.5}},"objectID":"B0C3572B-4AB1-4B8C-BDD2-B1EFA918CDC2","layers":[{"animations":[],"layers":[],"texturedRectangle":{"isBackgroundTexture":true,"singleTextureOpacity":1,"textureType":5,"textBaseline":0,"textXHeight":0,"isVerticalText":false},"initialState":{"affineTransform":[1,0,0,1,0,0],"masksToBounds":false,"rotation":0,"scale":1,"position":{"pointX":960.4999998626578,"pointY":540},"width":1923,"sublayerTransform":[1,0,0,0,0,1,0,0,0,0,1,0,0,0,0,1],"contentsRect":{"y":0,"x":0,"width":1,"height":1},"opacity":1,"edgeAntialiasingMask":0,"height":1082,"hidden":true,"anchorPoint":{"pointX":0.5,"pointY":0.5}},"texture":"7ECCBBADA95A810EA2401298EFB05CC2"},{"animations":[],"layers":[],"initialState":{"affineTransform":[1,0,0,1,0,0],"masksToBounds":false,"rotation":0,"scale":1,"position":{"pointX":960,"pointY":540},"width":1920,"sublayerTransform":[1,0,0,0,0,1,0,0,0,0,1,0,0,0,0,1],"contentsRect":{"y":0,"x":0,"width":1,"height":1},"opacity":1,"edgeAntialiasingMask":251658240,"height":1080,"hidden":false,"anchorPoint":{"pointX":0.5,"pointY":0.5}},"texture":"447D3461C58C508D2CD0D2E68FF39170"}]},"effects":[],"movie":{"startTime":0,"volume":0,"endTime":4.105000019073486,"isStreaming":false,"isAudioOnly":false,"asset":"scanning-saccade.mp4-0.0000-4.1050"},"duration":0,"type":"buildIn","name":"renderMovie","objectID":"B0C3572B-4AB1-4B8C-BDD2-B1EFA918CDC2"}],"duration":0.01,"type":"buildIn","name":"apple:movie-start","objectID":"B0C3572B-4AB1-4B8C-BDD2-B1EFA918CDC2"}],"automaticPlay":false,"hyperlinks":[{"url":"https://www.youtube.com/watch?v=YJbKieEC49M","targetRectangle":{"y":1031.748656570911,"x":1256.374938964844,"width":645.4248046875,"height":27.13623046875}},{"url":"http://bit.ly/1yTZWGN","targetRectangle":{"y":992.5889275670052,"x":1620.842712402344,"width":280.95703125,"height":27.13623046875}}],"accessibility":[{"text":"Fonte: https://www.youtube.com/watch?v=YJbKieEC49M","targetRectangle":{"y":1031.748656570911,"x":1169.758728027344,"width":732.041015625,"height":27.13623046875}},{"text":" Vídeo:  http://bit.ly/1yTZWGN","targetRectangle":{"y":992.5889275670052,"x":1521.247985839844,"width":380.5517578125,"height":27.13623046875}}],"baseLayer":{"animations":[],"initialState":{"affineTransform":[1,0,0,1,0,0],"masksToBounds":false,"rotation":0,"scale":1,"position":{"pointX":960,"pointY":540},"width":1920,"sublayerTransform":[1,0,0,0,0,1,0,0,0,0,1,0,0,0,0,1],"contentsRect":{"y":0,"x":0,"width":1,"height":1},"opacity":1,"edgeAntialiasingMask":251658240,"height":1080,"hidden":false,"anchorPoint":{"pointX":0.5,"pointY":0.5}},"layers":[{"animations":[],"initialState":{"affineTransform":[1,0,0,1,0,0],"masksToBounds":false,"rotation":0,"scale":1,"position":{"pointX":960,"pointY":540},"width":1920,"sublayerTransform":[1,0,0,0,0,1,0,0,0,0,1,0,0,0,0,1],"contentsRect":{"y":0,"x":0,"width":1,"height":1},"opacity":1,"edgeAntialiasingMask":251658240,"height":1080,"hidden":false,"anchorPoint":{"pointX":0.5,"pointY":0.5}},"layers":[{"animations":[],"initialState":{"affineTransform":[1,0,0,1,0,0],"masksToBounds":false,"rotation":0,"scale":1,"position":{"pointX":960,"pointY":540},"width":1920,"sublayerTransform":[1,0,0,0,0,1,0,0,0,0,1,0,0,0,0,1],"contentsRect":{"y":0,"x":0,"width":1,"height":1},"opacity":1,"edgeAntialiasingMask":251658240,"height":1080,"hidden":false,"anchorPoint":{"pointX":0.5,"pointY":0.5}},"layers":[{"animations":[],"layers":[],"texturedRectangle":{"isBackgroundTexture":true,"singleTextureOpacity":1,"textureType":1,"textBaseline":0,"textXHeight":0,"isVerticalText":false},"initialState":{"affineTransform":[1,0,0,1,0,0],"masksToBounds":false,"rotation":0,"scale":1,"position":{"pointX":960,"pointY":540},"width":1920,"sublayerTransform":[1,0,0,0,0,1,0,0,0,0,1,0,0,0,0,1],"contentsRect":{"y":0,"x":0,"width":1,"height":1},"opacity":1,"edgeAntialiasingMask":0,"height":1080,"hidden":false,"anchorPoint":{"pointX":0.5,"pointY":0.5}},"texture":"5BA6DF7ACEF516F7DAB78587CF30CE20"}]}]},{"animations":[],"initialState":{"affineTransform":[1,0,0,1,0,0],"masksToBounds":false,"rotation":0,"scale":1,"position":{"pointX":960,"pointY":540},"width":1920,"sublayerTransform":[1,0,0,0,0,1,0,0,0,0,1,0,0,0,0,1],"contentsRect":{"y":0,"x":0,"width":1,"height":1},"opacity":1,"edgeAntialiasingMask":251658240,"height":1080,"hidden":false,"anchorPoint":{"pointX":0.5,"pointY":0.5}},"layers":[{"animations":[],"initialState":{"affineTransform":[1,0,0,1,0,0],"masksToBounds":false,"rotation":0,"scale":1,"position":{"pointX":960.0000001373422,"pointY":540},"width":1920,"sublayerTransform":[1,0,0,0,0,1,0,0,0,0,1,0,0,0,0,1],"contentsRect":{"y":0,"x":0,"width":1,"height":1},"opacity":1,"edgeAntialiasingMask":251658240,"height":1080,"hidden":false,"anchorPoint":{"pointX":0.5,"pointY":0.5}},"objectID":"B0C3572B-4AB1-4B8C-BDD2-B1EFA918CDC2","layers":[{"animations":[],"layers":[],"texturedRectangle":{"isBackgroundTexture":true,"singleTextureOpacity":1,"textureType":5,"textBaseline":0,"textXHeight":0,"isVerticalText":false},"initialState":{"affineTransform":[1,0,0,1,0,0],"masksToBounds":false,"rotation":0,"scale":1,"position":{"pointX":960.4999998626578,"pointY":540},"width":1923,"sublayerTransform":[1,0,0,0,0,1,0,0,0,0,1,0,0,0,0,1],"contentsRect":{"y":0,"x":0,"width":1,"height":1},"opacity":1,"edgeAntialiasingMask":0,"height":1082,"hidden":false,"anchorPoint":{"pointX":0.5,"pointY":0.5}},"texture":"7ECCBBADA95A810EA2401298EFB05CC2"}]}]},{"animations":[],"initialState":{"affineTransform":[1,0,0,1,0,0],"masksToBounds":false,"rotation":0,"scale":1,"position":{"pointX":960,"pointY":540},"width":1920,"sublayerTransform":[1,0,0,0,0,1,0,0,0,0,1,0,0,0,0,1],"contentsRect":{"y":0,"x":0,"width":1,"height":1},"opacity":1,"edgeAntialiasingMask":251658240,"height":1080,"hidden":false,"anchorPoint":{"pointX":0.5,"pointY":0.5}},"layers":[{"animations":[],"initialState":{"affineTransform":[1,0,0,1,0,0],"masksToBounds":false,"rotation":0,"scale":1,"position":{"pointX":1514.315711021423,"pointY":1045.316772460938},"width":782.9680919647217,"sublayerTransform":[1,0,0,0,0,1,0,0,0,0,1,0,0,0,0,1],"contentsRect":{"y":0,"x":0,"width":1,"height":1},"opacity":1,"edgeAntialiasingMask":251658240,"height":35.13623178005219,"hidden":false,"anchorPoint":{"pointX":0.5,"pointY":0.5}},"objectID":"CAFF7A01-337B-47DE-A8A6-8083B3B3D100","layers":[{"animations":[],"layers":[],"texturedRectangle":{"singleTextureOpacity":1,"textXHeight":0.4502240349264706,"textBaseline":0.7358290535562179,"isBackgroundTexture":true,"isVerticalText":false,"textColor":[0.9999966025352478,0.9999999403953552,0.9999999403953552,1],"textureType":6},"initialState":{"affineTransform":[1,0,0,1,0,0],"masksToBounds":false,"rotation":0,"scale":1,"position":{"pointX":413.1683349609375,"pointY":17.25134342908859},"width":732,"sublayerTransform":[1,0,0,0,0,1,0,0,0,0,1,0,0,0,0,1],"contentsRect":{"y":0,"x":0,"width":1,"height":1},"opacity":1,"edgeAntialiasingMask":0,"height":34,"hidden":false,"anchorPoint":{"pointX":0.5,"pointY":0.5}},"texture":"1A8579A2224D6E44976C40D1C8926D33"}]}]},{"animations":[],"initialState":{"affineTransform":[1,0,0,1,0,0],"masksToBounds":false,"rotation":0,"scale":1,"position":{"pointX":960,"pointY":540},"width":1920,"sublayerTransform":[1,0,0,0,0,1,0,0,0,0,1,0,0,0,0,1],"contentsRect":{"y":0,"x":0,"width":1,"height":1},"opacity":1,"edgeAntialiasingMask":251658240,"height":1080,"hidden":false,"anchorPoint":{"pointX":0.5,"pointY":0.5}},"layers":[{"animations":[],"initialState":{"affineTransform":[1,0,0,1,0,0],"masksToBounds":false,"rotation":0,"scale":1,"position":{"pointX":1514.315711021423,"pointY":1006.157043457031},"width":782.9680919647217,"sublayerTransform":[1,0,0,0,0,1,0,0,0,0,1,0,0,0,0,1],"contentsRect":{"y":0,"x":0,"width":1,"height":1},"opacity":1,"edgeAntialiasingMask":251658240,"height":35.13623178005219,"hidden":false,"anchorPoint":{"pointX":0.5,"pointY":0.5}},"objectID":"CE0B11EC-2D86-408C-AA35-D1BFE70FCF6C","layers":[{"animations":[],"layers":[],"texturedRectangle":{"singleTextureOpacity":1,"textXHeight":0.4502240349264706,"textBaseline":0.7311311416766223,"isBackgroundTexture":true,"isVerticalText":false,"textColor":[0.9999966025352478,0.9999999403953552,0.9999999403953552,1],"textureType":6},"initialState":{"affineTransform":[1,0,0,1,0,0],"masksToBounds":false,"rotation":0,"scale":1,"position":{"pointX":587.6683349609375,"pointY":17.41107243299484},"width":383,"sublayerTransform":[1,0,0,0,0,1,0,0,0,0,1,0,0,0,0,1],"contentsRect":{"y":0,"x":0,"width":1,"height":1},"opacity":1,"edgeAntialiasingMask":0,"height":34,"hidden":false,"anchorPoint":{"pointX":0.5,"pointY":0.5}},"texture":"BA892B329981A31005A36E8FA9C1120D"}]}]}]}},{"effects":[{"beginTime":0,"baseLayer":{"animations":[],"initialState":{"affineTransform":[1,0,0,1,0,0],"masksToBounds":false,"rotation":0,"scale":1,"position":{"pointX":960,"pointY":540},"width":1920,"sublayerTransform":[1,0,0,0,0,1,0,0,0,0,1,0,0,0,0,1],"contentsRect":{"y":0,"x":0,"width":1,"height":1},"opacity":1,"edgeAntialiasingMask":251658240,"height":1080,"hidden":false,"anchorPoint":{"pointX":0.5,"pointY":0.5}},"objectID":"0","layers":[{"animations":[],"initialState":{"affineTransform":[1,0,0,1,0,0],"masksToBounds":false,"rotation":0,"scale":1,"position":{"pointX":960,"pointY":540},"width":1920,"sublayerTransform":[1,0,0,0,0,1,0,0,0,0,1,-0.0003500791246677598,0,0,0,1],"contentsRect":{"y":0,"x":0,"width":1,"height":1},"opacity":1,"edgeAntialiasingMask":251658240,"height":1080,"hidden":false,"anchorPoint":{"pointX":0.5,"pointY":0.5}},"layers":[{"animations":[],"layers":[],"texturedRectangle":{"isBackgroundTexture":false,"singleTextureOpacity":1,"textureType":0,"textBaseline":0,"textXHeight":0,"isVerticalText":false},"initialState":{"affineTransform":[1,0,0,1,0,0],"masksToBounds":false,"rotation":0,"scale":1,"position":{"pointX":960,"pointY":540},"width":1920,"sublayerTransform":[1,0,0,0,0,1,0,0,0,0,1,0,0,0,0,1],"contentsRect":{"y":0,"x":0,"width":1,"height":1},"opacity":1,"edgeAntialiasingMask":0,"height":1080,"hidden":false,"anchorPoint":{"pointX":0.5,"pointY":0.5}},"texture":"31875A1B00F89E47B08D92D0E8479265"},{"animations":[{"timeOffset":0,"from":{"scalar":false},"beginTime":0,"repeatCount":0,"fillMode":"both","property":"hidden","autoreverses":false,"duration":0.01,"to":{"scalar":true}}],"layers":[],"texturedRectangle":{"isBackgroundTexture":false,"singleTextureOpacity":1,"textureType":0,"textBaseline":0,"textXHeight":0,"isVerticalText":false},"initialState":{"affineTransform":[1,0,0,1,0,0],"masksToBounds":false,"rotation":0,"scale":1,"position":{"pointX":960,"pointY":540},"width":1920,"sublayerTransform":[1,0,0,0,0,1,0,0,0,0,1,0,0,0,0,1],"contentsRect":{"y":0,"x":0,"width":1,"height":1},"opacity":1,"edgeAntialiasingMask":0,"height":1080,"hidden":false,"anchorPoint":{"pointX":0.5,"pointY":0.5}},"texture":"844C2FF7E8E8A2713DCDCAE67EAAF34C"}]}]},"effects":[],"duration":0.01,"type":"transition","name":"none","objectID":"0"}],"automaticPlay":false,"hyperlinks":[{"url":"https://www.youtube.com/watch?v=YJbKieEC49M","targetRectangle":{"y":1031.748656570911,"x":1256.374938964844,"width":645.4248046875,"height":27.13623046875}},{"url":"http://bit.ly/1yTZWGN","targetRectangle":{"y":992.5889275670052,"x":1620.842712402344,"width":280.95703125,"height":27.13623046875}}],"accessibility":[{"text":"Fonte: https://www.youtube.com/watch?v=YJbKieEC49M","targetRectangle":{"y":1031.748656570911,"x":1169.758728027344,"width":732.041015625,"height":27.13623046875}},{"text":" Vídeo:  http://bit.ly/1yTZWGN","targetRectangle":{"y":992.5889275670052,"x":1521.247985839844,"width":380.5517578125,"height":27.13623046875}}],"baseLayer":{"animations":[],"initialState":{"affineTransform":[1,0,0,1,0,0],"masksToBounds":false,"rotation":0,"scale":1,"position":{"pointX":960,"pointY":540},"width":1920,"sublayerTransform":[1,0,0,0,0,1,0,0,0,0,1,0,0,0,0,1],"contentsRect":{"y":0,"x":0,"width":1,"height":1},"opacity":1,"edgeAntialiasingMask":251658240,"height":1080,"hidden":false,"anchorPoint":{"pointX":0.5,"pointY":0.5}},"objectID":"0","layers":[{"animations":[],"initialState":{"affineTransform":[1,0,0,1,0,0],"masksToBounds":false,"rotation":0,"scale":1,"position":{"pointX":960,"pointY":540},"width":1920,"sublayerTransform":[1,0,0,0,0,1,0,0,0,0,1,-0.0003500791246677598,0,0,0,1],"contentsRect":{"y":0,"x":0,"width":1,"height":1},"opacity":1,"edgeAntialiasingMask":251658240,"height":1080,"hidden":false,"anchorPoint":{"pointX":0.5,"pointY":0.5}},"layers":[{"animations":[],"layers":[],"texturedRectangle":{"isBackgroundTexture":false,"singleTextureOpacity":1,"textureType":0,"textBaseline":0,"textXHeight":0,"isVerticalText":false},"initialState":{"affineTransform":[1,0,0,1,0,0],"masksToBounds":false,"rotation":0,"scale":1,"position":{"pointX":960,"pointY":540},"width":1920,"sublayerTransform":[1,0,0,0,0,1,0,0,0,0,1,0,0,0,0,1],"contentsRect":{"y":0,"x":0,"width":1,"height":1},"opacity":1,"edgeAntialiasingMask":0,"height":1080,"hidden":false,"anchorPoint":{"pointX":0.5,"pointY":0.5}},"texture":"844C2FF7E8E8A2713DCDCAE67EAAF34C"}]}]}}]}